[{"eventId": 1, "startDate": 847, "eventMon": "MARCH    ", "sortIndex": 0, "eventType": "OUT", "stopDate": null, "patientId": 1064223, "summary": "MARCH     2008,OUT Outside radiology (R32)", "eventYear": 2008, "eventData": "OUT Outside radiology (R32)"}, {"eventId": 3, "startDate": 829, "eventMon": "MARCH    ", "sortIndex": 17, "eventType": "HML", "stopDate": null, "patientId": 1064223, "summary": "MARCH     2008,HML Home medication list (F69)", "eventYear": 2008, "eventData": "HML Home medication list (F69)"}, {"eventId": 4, "startDate": 847, "eventMon": "MARCH    ", "sortIndex": 0, "eventType": "OUT", "stopDate": null, "patientId": 1064223, "summary": "MARCH     2008,OUT Outside radiology (R32)", "eventYear": 2008, "eventData": "OUT Outside radiology (R32)"}, {"eventId": 5, "startDate": 1046, "eventMon": "OCTOBER  ", "sortIndex": 0, "eventType": "OUT", "stopDate": null, "patientId": 1064223, "summary": "OCTOBER   2008,OUT Outside radiology (R32)", "eventYear": 2008, "eventData": "OUT Outside radiology (R32)"}, {"eventId": 6, "startDate": 1046, "eventMon": "OCTOBER  ", "sortIndex": 0, "eventType": "OUT", "stopDate": null, "patientId": 1064223, "summary": "OCTOBER   2008,OUT Outside radiology (R32)", "eventYear": 2008, "eventData": "OUT Outside radiology (R32)"}, {"eventId": 9, "startDate": 1103, "eventMon": "DECEMBER ", "sortIndex": 10, "eventType": "ORD", "stopDate": null, "patientId": 1064223, "summary": "DECEMBER  2008,ORD Orders (O52)", "eventYear": 2008, "eventData": "ORD Orders (O52)"}, {"eventId": 11, "startDate": 1103, "eventMon": "DECEMBER ", "sortIndex": 17, "eventType": "HML", "stopDate": null, "patientId": 1064223, "summary": "DECEMBER  2008,HML Home medication list (F69)", "eventYear": 2008, "eventData": "HML Home medication list (F69)"}, {"eventId": 14, "startDate": 920, "eventMon": "JUNE     ", "sortIndex": 17, "eventType": "HML", "stopDate": null, "patientId": 1064223, "summary": "JUNE      2008,HML Home medication list (F69)", "eventYear": 2008, "eventData": "HML Home medication list (F69)"}, {"eventId": 15, "startDate": 920, "eventMon": "JUNE     ", "sortIndex": 10, "eventType": "ORD", "stopDate": null, "patientId": 1064223, "summary": "JUNE      2008,ORD Orders (O52)", "eventYear": 2008, "eventData": "ORD Orders (O52)"}, {"eventId": 16, "startDate": 920, "eventMon": "JUNE     ", "sortIndex": 17, "eventType": "HML", "stopDate": null, "patientId": 1064223, "summary": "JUNE      2008,HML Home medication list (F69)", "eventYear": 2008, "eventData": "HML Home medication list (F69)"}, {"eventId": 18, "startDate": 990, "eventMon": "AUGUST   ", "sortIndex": 120, "eventType": "OUT", "stopDate": null, "patientId": 1064223, "summary": "AUGUST    2008,OUT Outside insurance information (R37)", "eventYear": 2008, "eventData": "OUT Outside insurance information (R37)"}, {"eventId": 22, "startDate": 731, "eventMon": "NOVEMBER ", "sortIndex": 17, "eventType": "HML", "stopDate": null, "patientId": 1064223, "summary": "NOVEMBER  2007,HML Home medication list (F69)", "eventYear": 2007, "eventData": "HML Home medication list (F69)"}, {"eventId": 23, "startDate": 731, "eventMon": "NOVEMBER ", "sortIndex": 10, "eventType": "ORD", "stopDate": null, "patientId": 1064223, "summary": "NOVEMBER  2007,ORD Orders (O52)", "eventYear": 2007, "eventData": "ORD Orders (O52)"}, {"eventId": 24, "startDate": 744, "eventMon": "DECEMBER ", "sortIndex": 0, "eventType": "OUT", "stopDate": null, "patientId": 1064223, "summary": "DECEMBER  2007,OUT Outside radiology (R32)", "eventYear": 2007, "eventData": "OUT Outside radiology (R32)"}, {"eventId": 25, "startDate": 742, "eventMon": "DECEMBER ", "sortIndex": 0, "eventType": "OUT", "stopDate": null, "patientId": 1064223, "summary": "DECEMBER  2007,OUT Outside radiology (R32)", "eventYear": 2007, "eventData": "OUT Outside radiology (R32)"}, {"eventId": 27, "startDate": 521, "eventMon": "MAY      ", "sortIndex": 0, "eventType": "OUT", "stopDate": null, "patientId": 1064223, "summary": "MAY       2007,OUT Outside radiology (R32)", "eventYear": 2007, "eventData": "OUT Outside radiology (R32)"}, {"eventId": 31, "startDate": 542, "eventMon": "MAY      ", "sortIndex": 17, "eventType": "HML", "stopDate": null, "patientId": 1064223, "summary": "MAY       2007,HML Home medication list (F69)", "eventYear": 2007, "eventData": "HML Home medication list (F69)"}, {"eventId": 32, "startDate": 542, "eventMon": "MAY      ", "sortIndex": 40, "eventType": "ADM", "stopDate": null, "patientId": 1064223, "summary": "MAY       2007,ADM Consent-dx/therap proc (A29)", "eventYear": 2007, "eventData": "ADM Consent-dx/therap proc (A29)"}, {"eventId": 35, "startDate": 562, "eventMon": "JUNE     ", "sortIndex": 15, "eventType": "MSK", "stopDate": null, "patientId": 1064223, "summary": "JUNE      2007,MSK Mskcc correspondence (P00)", "eventYear": 2007, "eventData": "MSK Mskcc correspondence (P00)"}, {"eventId": 37, "startDate": 568, "eventMon": "JUNE     ", "sortIndex": 5, "eventType": "OUT", "stopDate": null, "patientId": 1064223, "summary": "JUNE      2007,OUT Outside md correspondence (R36)", "eventYear": 2007, "eventData": "OUT Outside md correspondence (R36)"}, {"eventId": 39, "startDate": 592, "eventMon": "JULY     ", "sortIndex": 0, "eventType": "OUT", "stopDate": null, "patientId": 1064223, "summary": "JULY      2007,OUT Outside radiology (R32)", "eventYear": 2007, "eventData": "OUT Outside radiology (R32)"}, {"eventId": 40, "startDate": 597, "eventMon": "JULY     ", "sortIndex": 0, "eventType": "OUT", "stopDate": null, "patientId": 1064223, "summary": "JULY      2007,OUT Outside radiology (R32)", "eventYear": 2007, "eventData": "OUT Outside radiology (R32)"}, {"eventId": 41, "startDate": 597, "eventMon": "JULY     ", "sortIndex": 0, "eventType": "OUT", "stopDate": null, "patientId": 1064223, "summary": "JULY      2007,OUT Outside radiology (R32)", "eventYear": 2007, "eventData": "OUT Outside radiology (R32)"}, {"eventId": 56, "startDate": 83, "eventMon": "FEBRUARY ", "sortIndex": 7, "eventType": "LAB", "stopDate": null, "patientId": 1064223, "summary": "FEBRUARY  2006,LAB Lab new data outpatient (T36)", "eventYear": 2006, "eventData": "LAB Lab new data outpatient (T36)"}, {"eventId": 57, "startDate": 80, "eventMon": "FEBRUARY ", "sortIndex": 7, "eventType": "LAB", "stopDate": null, "patientId": 1064223, "summary": "FEBRUARY  2006,LAB Lab new data outpatient (T36)", "eventYear": 2006, "eventData": "LAB Lab new data outpatient (T36)"}, {"eventId": 62, "startDate": 50, "eventMon": "JANUARY  ", "sortIndex": 108, "eventType": "RAD", "stopDate": null, "patientId": 1064223, "summary": "JANUARY   2006,RAD Diagnostic radiology (T10)", "eventYear": 2006, "eventData": "RAD Diagnostic radiology (T10)"}, {"eventId": 75, "startDate": 58, "eventMon": "JANUARY  ", "sortIndex": 111, "eventType": "ASM", "stopDate": null, "patientId": 1064223, "summary": "JANUARY   2006,ASM Progress note (P32)", "eventYear": 2006, "eventData": "ASM Progress note (P32)"}, {"eventId": 78, "startDate": 45, "eventMon": "JANUARY  ", "sortIndex": 4, "eventType": "OUT", "stopDate": null, "patientId": 1064223, "summary": "JANUARY   2006,OUT Non-mskcc correspondence (P02)", "eventYear": 2006, "eventData": "OUT Non-mskcc correspondence (P02)"}, {"eventId": 106, "startDate": 58, "eventMon": "JANUARY  ", "sortIndex": 47, "eventType": "FLW", "stopDate": null, "patientId": 1064223, "summary": "JANUARY   2006,FLW Vital signs (F01)", "eventYear": 2006, "eventData": "FLW Vital signs (F01)"}, {"eventId": 108, "startDate": 50, "eventMon": "JANUARY  ", "sortIndex": 7, "eventType": "LAB", "stopDate": null, "patientId": 1064223, "summary": "JANUARY   2006,LAB Lab new data outpatient (T36)", "eventYear": 2006, "eventData": "LAB Lab new data outpatient (T36)"}, {"eventId": 109, "startDate": 45, "eventMon": "JANUARY  ", "sortIndex": 4, "eventType": "OUT", "stopDate": null, "patientId": 1064223, "summary": "JANUARY   2006,OUT Non-mskcc correspondence (P02)", "eventYear": 2006, "eventData": "OUT Non-mskcc correspondence (P02)"}, {"eventId": 110, "startDate": 57, "eventMon": "JANUARY  ", "sortIndex": 4, "eventType": "OUT", "stopDate": null, "patientId": 1064223, "summary": "JANUARY   2006,OUT Non-mskcc correspondence (P02)", "eventYear": 2006, "eventData": "OUT Non-mskcc correspondence (P02)"}, {"eventId": 112, "startDate": 58, "eventMon": "JANUARY  ", "sortIndex": 10, "eventType": "ORD", "stopDate": null, "patientId": 1064223, "summary": "JANUARY   2006,ORD Orders (O52)", "eventYear": 2006, "eventData": "ORD Orders (O52)"}, {"eventId": 113, "startDate": 58, "eventMon": "JANUARY  ", "sortIndex": 10, "eventType": "ORD", "stopDate": null, "patientId": 1064223, "summary": "JANUARY   2006,ORD Orders (O52)", "eventYear": 2006, "eventData": "ORD Orders (O52)"}, {"eventId": 119, "startDate": 318, "eventMon": "OCTOBER  ", "sortIndex": 10, "eventType": "ORD", "stopDate": null, "patientId": 1064223, "summary": "OCTOBER   2006,ORD Orders (O52)", "eventYear": 2006, "eventData": "ORD Orders (O52)"}, {"eventId": 120, "startDate": 318, "eventMon": "OCTOBER  ", "sortIndex": 17, "eventType": "HML", "stopDate": null, "patientId": 1064223, "summary": "OCTOBER   2006,HML Home medication list (F69)", "eventYear": 2006, "eventData": "HML Home medication list (F69)"}, {"eventId": 126, "startDate": 3070, "eventMon": "APRIL    ", "sortIndex": 10, "eventType": "ORD", "stopDate": null, "patientId": 1064223, "summary": "APRIL     2014,ORD Orders (O52)", "eventYear": 2014, "eventData": "ORD Orders (O52)"}, {"eventId": 127, "startDate": 3070, "eventMon": "APRIL    ", "sortIndex": 10, "eventType": "ORD", "stopDate": null, "patientId": 1064223, "summary": "APRIL     2014,ORD Orders (O52)", "eventYear": 2014, "eventData": "ORD Orders (O52)"}, {"eventId": 128, "startDate": 3070, "eventMon": "APRIL    ", "sortIndex": 10, "eventType": "ORD", "stopDate": null, "patientId": 1064223, "summary": "APRIL     2014,ORD Orders (O52)", "eventYear": 2014, "eventData": "ORD Orders (O52)"}, {"eventId": 129, "startDate": 3070, "eventMon": "APRIL    ", "sortIndex": 10, "eventType": "ORD", "stopDate": null, "patientId": 1064223, "summary": "APRIL     2014,ORD Orders (O52)", "eventYear": 2014, "eventData": "ORD Orders (O52)"}, {"eventId": 131, "startDate": 3070, "eventMon": "APRIL    ", "sortIndex": 17, "eventType": "HML", "stopDate": null, "patientId": 1064223, "summary": "APRIL     2014,HML Home medication list (F69)", "eventYear": 2014, "eventData": "HML Home medication list (F69)"}, {"eventId": 134, "startDate": 29, "eventMon": "DECEMBER ", "sortIndex": 0, "eventType": "OUT", "stopDate": null, "patientId": 1064223, "summary": "DECEMBER  2005,OUT Outside radiology (R32)", "eventYear": 2005, "eventData": "OUT Outside radiology (R32)"}, {"eventId": 149, "startDate": 29, "eventMon": "DECEMBER ", "sortIndex": 0, "eventType": "OUT", "stopDate": null, "patientId": 1064223, "summary": "DECEMBER  2005,OUT Outside radiology (R32)", "eventYear": 2005, "eventData": "OUT Outside radiology (R32)"}, {"eventId": 150, "startDate": 29, "eventMon": "DECEMBER ", "sortIndex": 0, "eventType": "OUT", "stopDate": null, "patientId": 1064223, "summary": "DECEMBER  2005,OUT Outside radiology (R32)", "eventYear": 2005, "eventData": "OUT Outside radiology (R32)"}, {"eventId": 151, "startDate": 29, "eventMon": "DECEMBER ", "sortIndex": 0, "eventType": "OUT", "stopDate": null, "patientId": 1064223, "summary": "DECEMBER  2005,OUT Outside radiology (R32)", "eventYear": 2005, "eventData": "OUT Outside radiology (R32)"}, {"eventId": 152, "startDate": 29, "eventMon": "DECEMBER ", "sortIndex": 0, "eventType": "OUT", "stopDate": null, "patientId": 1064223, "summary": "DECEMBER  2005,OUT Outside radiology (R32)", "eventYear": 2005, "eventData": "OUT Outside radiology (R32)"}, {"eventId": 153, "startDate": 23, "eventMon": "DECEMBER ", "sortIndex": 129, "eventType": "RAD", "stopDate": null, "patientId": 1064223, "summary": "DECEMBER  2005,RAD Ct scan (T11)", "eventYear": 2005, "eventData": "RAD Ct scan (T11)"}, {"eventId": 154, "startDate": 23, "eventMon": "DECEMBER ", "sortIndex": 130, "eventType": "ORD", "stopDate": null, "patientId": 1064223, "summary": "DECEMBER  2005,ORD Contrast & lab orders - iv-ct (O84)", "eventYear": 2005, "eventData": "ORD Contrast & lab orders - iv-ct (O84)"}, {"eventId": 157, "startDate": 23, "eventMon": "DECEMBER ", "sortIndex": 134, "eventType": "FLW", "stopDate": null, "patientId": 1064223, "summary": "DECEMBER  2005,FLW Ct / mri / ivp medication admin record (F63)", "eventYear": 2005, "eventData": "FLW Ct / mri / ivp medication admin record (F63)"}, {"eventId": 158, "startDate": 23, "eventMon": "DECEMBER ", "sortIndex": 132, "eventType": "ADM", "stopDate": null, "patientId": 1064223, "summary": "DECEMBER  2005,ADM Question-contrast media (A35)", "eventYear": 2005, "eventData": "ADM Question-contrast media (A35)"}, {"eventId": 159, "startDate": -390, "eventMon": "NOVEMBER ", "sortIndex": 0, "eventType": "OUT", "stopDate": null, "patientId": 1064223, "summary": "NOVEMBER  2004,OUT Outside radiology (R32)", "eventYear": 2004, "eventData": "OUT Outside radiology (R32)"}, {"eventId": 160, "startDate": -390, "eventMon": "NOVEMBER ", "sortIndex": 0, "eventType": "OUT", "stopDate": null, "patientId": 1064223, "summary": "NOVEMBER  2004,OUT Outside radiology (R32)", "eventYear": 2004, "eventData": "OUT Outside radiology (R32)"}, {"eventId": 161, "startDate": -404, "eventMon": "OCTOBER  ", "sortIndex": 0, "eventType": "OUT", "stopDate": null, "patientId": 1064223, "summary": "OCTOBER   2004,OUT Outside radiology (R32)", "eventYear": 2004, "eventData": "OUT Outside radiology (R32)"}, {"eventId": 162, "startDate": -417, "eventMon": "OCTOBER  ", "sortIndex": 4, "eventType": "OUT", "stopDate": null, "patientId": 1064223, "summary": "OCTOBER   2004,OUT Non-mskcc correspondence (P02)", "eventYear": 2004, "eventData": "OUT Non-mskcc correspondence (P02)"}, {"eventId": 163, "startDate": -417, "eventMon": "OCTOBER  ", "sortIndex": 0, "eventType": "OUT", "stopDate": null, "patientId": 1064223, "summary": "OCTOBER   2004,OUT Outside radiology (R32)", "eventYear": 2004, "eventData": "OUT Outside radiology (R32)"}, {"eventId": 165, "startDate": -2513, "eventMon": "JANUARY  ", "sortIndex": 4, "eventType": "OUT", "stopDate": null, "patientId": 1064223, "summary": "JANUARY   1999,OUT Non-mskcc correspondence (P02)", "eventYear": 1999, "eventData": "OUT Non-mskcc correspondence (P02)"}, {"eventId": 191, "startDate": 2871, "eventMon": "OCTOBER  ", "sortIndex": 7, "eventType": "LAB", "stopDate": null, "patientId": 1064223, "summary": "OCTOBER   2013,LAB Lab new data outpatient (T36)", "eventYear": 2013, "eventData": "LAB Lab new data outpatient (T36)"}, {"eventId": 192, "startDate": 2871, "eventMon": "OCTOBER  ", "sortIndex": 108, "eventType": "RAD", "stopDate": null, "patientId": 1064223, "summary": "OCTOBER   2013,RAD Diagnostic radiology (T10)", "eventYear": 2013, "eventData": "RAD Diagnostic radiology (T10)"}, {"eventId": 197, "startDate": 2865, "eventMon": "OCTOBER  ", "sortIndex": 4, "eventType": "OUT", "stopDate": null, "patientId": 1064223, "summary": "OCTOBER   2013,OUT Non-mskcc correspondence (P02)", "eventYear": 2013, "eventData": "OUT Non-mskcc correspondence (P02)"}, {"eventId": 199, "startDate": 2871, "eventMon": "OCTOBER  ", "sortIndex": 10, "eventType": "ORD", "stopDate": null, "patientId": 1064223, "summary": "OCTOBER   2013,ORD Orders (O52)", "eventYear": 2013, "eventData": "ORD Orders (O52)"}, {"eventId": 200, "startDate": 2873, "eventMon": "OCTOBER  ", "sortIndex": 10, "eventType": "ORD", "stopDate": null, "patientId": 1064223, "summary": "OCTOBER   2013,ORD Orders (O52)", "eventYear": 2013, "eventData": "ORD Orders (O52)"}, {"eventId": 201, "startDate": 2878, "eventMon": "OCTOBER  ", "sortIndex": 10, "eventType": "ORD", "stopDate": null, "patientId": 1064223, "summary": "OCTOBER   2013,ORD Orders (O52)", "eventYear": 2013, "eventData": "ORD Orders (O52)"}, {"eventId": 202, "startDate": 2887, "eventMon": "OCTOBER  ", "sortIndex": 10, "eventType": "ORD", "stopDate": null, "patientId": 1064223, "summary": "OCTOBER   2013,ORD Orders (O52)", "eventYear": 2013, "eventData": "ORD Orders (O52)"}, {"eventId": 206, "startDate": 2865, "eventMon": "OCTOBER  ", "sortIndex": 16, "eventType": "NURS", "stopDate": null, "patientId": 1064223, "summary": "OCTOBER   2013,NURS Telephone/electronic commun nursing (K84)", "eventYear": 2013, "eventData": "NURS Telephone/electronic commun nursing (K84)"}, {"eventId": 207, "startDate": 2885, "eventMon": "OCTOBER  ", "sortIndex": 16, "eventType": "NURS", "stopDate": null, "patientId": 1064223, "summary": "OCTOBER   2013,NURS Telephone/electronic commun nursing (K84)", "eventYear": 2013, "eventData": "NURS Telephone/electronic commun nursing (K84)"}, {"eventId": 208, "startDate": 2891, "eventMon": "OCTOBER  ", "sortIndex": 16, "eventType": "NURS", "stopDate": null, "patientId": 1064223, "summary": "OCTOBER   2013,NURS Telephone/electronic commun nursing (K84)", "eventYear": 2013, "eventData": "NURS Telephone/electronic commun nursing (K84)"}, {"eventId": 212, "startDate": 2871, "eventMon": "OCTOBER  ", "sortIndex": 17, "eventType": "HML", "stopDate": null, "patientId": 1064223, "summary": "OCTOBER   2013,HML Home medication list (F69)", "eventYear": 2013, "eventData": "HML Home medication list (F69)"}, {"eventId": 213, "startDate": 2871, "eventMon": "OCTOBER  ", "sortIndex": 17, "eventType": "HML", "stopDate": null, "patientId": 1064223, "summary": "OCTOBER   2013,HML Home medication list (F69)", "eventYear": 2013, "eventData": "HML Home medication list (F69)"}, {"eventId": 214, "startDate": 2887, "eventMon": "OCTOBER  ", "sortIndex": 17, "eventType": "HML", "stopDate": null, "patientId": 1064223, "summary": "OCTOBER   2013,HML Home medication list (F69)", "eventYear": 2013, "eventData": "HML Home medication list (F69)"}, {"eventId": 215, "startDate": 2871, "eventMon": "OCTOBER  ", "sortIndex": 47, "eventType": "FLW", "stopDate": null, "patientId": 1064223, "summary": "OCTOBER   2013,FLW Vital signs (F01)", "eventYear": 2013, "eventData": "FLW Vital signs (F01)"}, {"eventId": 220, "startDate": 2759, "eventMon": "JUNE     ", "sortIndex": 5, "eventType": "OUT", "stopDate": null, "patientId": 1064223, "summary": "JUNE      2013,OUT Outside md correspondence (R36)", "eventYear": 2013, "eventData": "OUT Outside md correspondence (R36)"}, {"eventId": 221, "startDate": 2759, "eventMon": "JUNE     ", "sortIndex": 1, "eventType": "OUT", "stopDate": null, "patientId": 1064223, "summary": "JUNE      2013,OUT Outside lab (R31)", "eventYear": 2013, "eventData": "OUT Outside lab (R31)"}, {"eventId": 232, "startDate": 2810, "eventMon": "AUGUST   ", "sortIndex": 8, "eventType": "RAD", "stopDate": null, "patientId": 1064223, "summary": "AUGUST    2013,RAD Nuclear med (T14)", "eventYear": 2013, "eventData": "RAD Nuclear med (T14)"}, {"eventId": 233, "startDate": 2807, "eventMon": "AUGUST   ", "sortIndex": 4, "eventType": "OUT", "stopDate": null, "patientId": 1064223, "summary": "AUGUST    2013,OUT Non-mskcc correspondence (P02)", "eventYear": 2013, "eventData": "OUT Non-mskcc correspondence (P02)"}, {"eventId": 234, "startDate": 2809, "eventMon": "AUGUST   ", "sortIndex": 51, "eventType": "MSK", "stopDate": null, "patientId": 1064223, "summary": "AUGUST    2013,MSK E-sig fax cover page (PQ6)", "eventYear": 2013, "eventData": "MSK E-sig fax cover page (PQ6)"}, {"eventId": 235, "startDate": 2809, "eventMon": "AUGUST   ", "sortIndex": 51, "eventType": "MSK", "stopDate": null, "patientId": 1064223, "summary": "AUGUST    2013,MSK E-sig fax cover page (PQ6)", "eventYear": 2013, "eventData": "MSK E-sig fax cover page (PQ6)"}, {"eventId": 236, "startDate": 2809, "eventMon": "AUGUST   ", "sortIndex": 51, "eventType": "MSK", "stopDate": null, "patientId": 1064223, "summary": "AUGUST    2013,MSK E-sig fax cover page (PQ6)", "eventYear": 2013, "eventData": "MSK E-sig fax cover page (PQ6)"}, {"eventId": 237, "startDate": 2809, "eventMon": "AUGUST   ", "sortIndex": 51, "eventType": "MSK", "stopDate": null, "patientId": 1064223, "summary": "AUGUST    2013,MSK E-sig fax cover page (PQ6)", "eventYear": 2013, "eventData": "MSK E-sig fax cover page (PQ6)"}, {"eventId": 239, "startDate": 2809, "eventMon": "AUGUST   ", "sortIndex": 10, "eventType": "ORD", "stopDate": null, "patientId": 1064223, "summary": "AUGUST    2013,ORD Orders (O52)", "eventYear": 2013, "eventData": "ORD Orders (O52)"}, {"eventId": 240, "startDate": 2810, "eventMon": "AUGUST   ", "sortIndex": 10, "eventType": "ORD", "stopDate": null, "patientId": 1064223, "summary": "AUGUST    2013,ORD Orders (O52)", "eventYear": 2013, "eventData": "ORD Orders (O52)"}, {"eventId": 241, "startDate": 2809, "eventMon": "AUGUST   ", "sortIndex": 10, "eventType": "ORD", "stopDate": null, "patientId": 1064223, "summary": "AUGUST    2013,ORD Orders (O52)", "eventYear": 2013, "eventData": "ORD Orders (O52)"}, {"eventId": 242, "startDate": 2810, "eventMon": "AUGUST   ", "sortIndex": 10, "eventType": "ORD", "stopDate": null, "patientId": 1064223, "summary": "AUGUST    2013,ORD Orders (O52)", "eventYear": 2013, "eventData": "ORD Orders (O52)"}, {"eventId": 243, "startDate": 2809, "eventMon": "AUGUST   ", "sortIndex": 10, "eventType": "ORD", "stopDate": null, "patientId": 1064223, "summary": "AUGUST    2013,ORD Orders (O52)", "eventYear": 2013, "eventData": "ORD Orders (O52)"}, {"eventId": 246, "startDate": 2832, "eventMon": "AUGUST   ", "sortIndex": 16, "eventType": "NURS", "stopDate": null, "patientId": 1064223, "summary": "AUGUST    2013,NURS Telephone/electronic commun nursing (K84)", "eventYear": 2013, "eventData": "NURS Telephone/electronic commun nursing (K84)"}, {"eventId": 247, "startDate": 2814, "eventMon": "AUGUST   ", "sortIndex": 16, "eventType": "NURS", "stopDate": null, "patientId": 1064223, "summary": "AUGUST    2013,NURS Telephone/electronic commun nursing (K84)", "eventYear": 2013, "eventData": "NURS Telephone/electronic commun nursing (K84)"}, {"eventId": 250, "startDate": 2809, "eventMon": "AUGUST   ", "sortIndex": 17, "eventType": "HML", "stopDate": null, "patientId": 1064223, "summary": "AUGUST    2013,HML Home medication list (F69)", "eventYear": 2013, "eventData": "HML Home medication list (F69)"}, {"eventId": 252, "startDate": 2787, "eventMon": "JULY     ", "sortIndex": 0, "eventType": "OUT", "stopDate": null, "patientId": 1064223, "summary": "JULY      2013,OUT Outside radiology (R32)", "eventYear": 2013, "eventData": "OUT Outside radiology (R32)"}, {"eventId": 253, "startDate": 2801, "eventMon": "JULY     ", "sortIndex": 5, "eventType": "OUT", "stopDate": null, "patientId": 1064223, "summary": "JULY      2013,OUT Outside md correspondence (R36)", "eventYear": 2013, "eventData": "OUT Outside md correspondence (R36)"}, {"eventId": 254, "startDate": 2787, "eventMon": "JULY     ", "sortIndex": 0, "eventType": "OUT", "stopDate": null, "patientId": 1064223, "summary": "JULY      2013,OUT Outside radiology (R32)", "eventYear": 2013, "eventData": "OUT Outside radiology (R32)"}, {"eventId": 255, "startDate": 2790, "eventMon": "JULY     ", "sortIndex": 0, "eventType": "OUT", "stopDate": null, "patientId": 1064223, "summary": "JULY      2013,OUT Outside radiology (R32)", "eventYear": 2013, "eventData": "OUT Outside radiology (R32)"}, {"eventId": 256, "startDate": 2801, "eventMon": "JULY     ", "sortIndex": 4, "eventType": "OUT", "stopDate": null, "patientId": 1064223, "summary": "JULY      2013,OUT Non-mskcc correspondence (P02)", "eventYear": 2013, "eventData": "OUT Non-mskcc correspondence (P02)"}, {"eventId": 257, "startDate": -4044, "eventMon": "NOVEMBER ", "sortIndex": 4, "eventType": "OUT", "stopDate": null, "patientId": 1064223, "summary": "NOVEMBER  1994,OUT Non-mskcc correspondence (P02)", "eventYear": 1994, "eventData": "OUT Non-mskcc correspondence (P02)"}, {"eventId": 262, "startDate": 2871, "eventMon": "OCTOBER", "sortIndex": 631, "eventType": "Diagnostic", "stopDate": null, "patientId": 1064223, "summary": "OCTOBER 2013,Diagnostic Comprehensive Metabolic Panel,Laboratory,PST_Core_Orders", "eventYear": 2013, "eventData": "Diagnostic Comprehensive Metabolic Panel"}, {"eventId": 263, "startDate": 2871, "eventMon": "OCTOBER", "sortIndex": 635, "eventType": "Diagnostic", "stopDate": null, "patientId": 1064223, "summary": "OCTOBER 2013,Diagnostic Complete Blood Count,Laboratory,PST_Core_Orders", "eventYear": 2013, "eventData": "Diagnostic Complete Blood Count"}, {"eventId": 266, "startDate": 2878, "eventMon": "OCTOBER", "sortIndex": 663, "eventType": "Other", "stopDate": null, "patientId": 1064223, "summary": "OCTOBER 2013,Other Diet,Diet,SDH_PACU_Breast_OP_PostOP", "eventYear": 2013, "eventData": "Other Diet"}, {"eventId": 276, "startDate": 2878, "eventMon": "OCTOBER", "sortIndex": 662, "eventType": "Medication", "stopDate": null, "patientId": 1064223, "summary": "OCTOBER 2013,Medication Dexamethasone INJ,,SDH_PACU_Breast_OP_PostOP", "eventYear": 2013, "eventData": "Medication Dexamethasone INJ"}, {"eventId": 299, "startDate": 80, "eventMon": "FEBRUARY", "sortIndex": 758, "eventType": "Diagnostic", "stopDate": null, "patientId": 1064223, "summary": "FEBRUARY 2006,Diagnostic CBC with Automated Diff,,", "eventYear": 2006, "eventData": "Diagnostic CBC with Automated Diff"}, {"eventId": 300, "startDate": 80, "eventMon": "FEBRUARY", "sortIndex": 631, "eventType": "Diagnostic", "stopDate": null, "patientId": 1064223, "summary": "FEBRUARY 2006,Diagnostic Comprehensive Metabolic Panel,,", "eventYear": 2006, "eventData": "Diagnostic Comprehensive Metabolic Panel"}, {"eventId": 301, "startDate": 80, "eventMon": "FEBRUARY", "sortIndex": 635, "eventType": "Diagnostic", "stopDate": null, "patientId": 1064223, "summary": "FEBRUARY 2006,Diagnostic Complete Blood Count,,", "eventYear": 2006, "eventData": "Diagnostic Complete Blood Count"}, {"eventId": 302, "startDate": 80, "eventMon": "FEBRUARY", "sortIndex": 632, "eventType": "Diagnostic", "stopDate": null, "patientId": 1064223, "summary": "FEBRUARY 2006,Diagnostic Cancer Antigen 15-3,,", "eventYear": 2006, "eventData": "Diagnostic Cancer Antigen 15-3"}, {"eventId": 313, "startDate": 57, "eventMon": "JANUARY", "sortIndex": 738, "eventType": "Other", "stopDate": null, "patientId": 1064223, "summary": "JANUARY 2006,Other Orders Signoff,,", "eventYear": 2006, "eventData": "Other Orders Signoff"}, {"eventId": 327, "startDate": 58, "eventMon": "JANUARY", "sortIndex": 738, "eventType": "Other", "stopDate": null, "patientId": 1064223, "summary": "JANUARY 2006,Other Orders Signoff,,", "eventYear": 2006, "eventData": "Other Orders Signoff"}, {"eventId": 328, "startDate": 58, "eventMon": "JANUARY", "sortIndex": 738, "eventType": "Other", "stopDate": null, "patientId": 1064223, "summary": "JANUARY 2006,Other Orders Signoff,,", "eventYear": 2006, "eventData": "Other Orders Signoff"}, {"eventId": 334, "startDate": 57, "eventMon": "JANUARY", "sortIndex": 663, "eventType": "Other", "stopDate": null, "patientId": 1064223, "summary": "JANUARY 2006,Other Diet,Diet,SDH-PACU_Breast_Surg_Admission", "eventYear": 2006, "eventData": "Other Diet"}, {"eventId": 338, "startDate": 50, "eventMon": "JANUARY", "sortIndex": 758, "eventType": "Diagnostic", "stopDate": null, "patientId": 1064223, "summary": "JANUARY 2006,Diagnostic CBC with Automated Diff,,", "eventYear": 2006, "eventData": "Diagnostic CBC with Automated Diff"}, {"eventId": 355, "startDate": 50, "eventMon": "JANUARY", "sortIndex": 631, "eventType": "Diagnostic", "stopDate": null, "patientId": 1064223, "summary": "JANUARY 2006,Diagnostic Comprehensive Metabolic Panel,,", "eventYear": 2006, "eventData": "Diagnostic Comprehensive Metabolic Panel"}, {"eventId": 356, "startDate": 50, "eventMon": "JANUARY", "sortIndex": 633, "eventType": "Diagnostic", "stopDate": null, "patientId": 1064223, "summary": "JANUARY 2006,Diagnostic PT&APTT,,", "eventYear": 2006, "eventData": "Diagnostic PT&APTT"}, {"eventId": 357, "startDate": 50, "eventMon": "JANUARY", "sortIndex": 635, "eventType": "Diagnostic", "stopDate": null, "patientId": 1064223, "summary": "JANUARY 2006,Diagnostic Complete Blood Count,,", "eventYear": 2006, "eventData": "Diagnostic Complete Blood Count"}, {"eventId": 360, "startDate": 23, "eventMon": "DECEMBER", "sortIndex": 981, "eventType": "Diagnostic", "stopDate": null, "patientId": 1064223, "summary": "DECEMBER 2005,Diagnostic CT:Chest/Abdomen/Pelvis w/ Contrast,,", "eventYear": 2005, "eventData": "Diagnostic CT:Chest/Abdomen/Pelvis w/ Contrast"}]